fsm_load_modal_composites.py
fsm_load_modal_composites-1.0.1.dist-info/DESCRIPTION.rst
fsm_load_modal_composites-1.0.1.dist-info/METADATA
fsm_load_modal_composites-1.0.1.dist-info/RECORD
fsm_load_modal_composites-1.0.1.dist-info/WHEEL
fsm_load_modal_composites-1.0.1.dist-info/metadata.json
fsm_load_modal_composites-1.0.1.dist-info/top_level.txt
