Metadata-Version: 2.0
Name: fsm-load-modal-composites
Version: 1.0.1
Summary: Python library that loads modal composites from the file containing the parametric model of buckling and free vibration in prismatic shell structures, as computed by the fsm_eigenvalue project.
Home-page: https://github.com/petarmaric/fsm_load_modal_composites
Author: Petar Maric
Author-email: petarmaric@uns.ac.rs
License: BSD
Platform: any
Classifier: Development Status :: 5 - Production/Stable
Classifier: Intended Audience :: Developers
Classifier: Intended Audience :: Science/Research
Classifier: License :: OSI Approved :: BSD License
Classifier: Operating System :: OS Independent
Classifier: Programming Language :: Python :: 2.7
Classifier: Topic :: Database
Classifier: Topic :: Scientific/Engineering
Classifier: Topic :: Scientific/Engineering :: Physics
Requires-Dist: PyYAML (~=3.11)
Requires-Dist: dynamic-pytables-where-condition (~=1.0)
Requires-Dist: tables (~=3.2)
